README.md
setup.py
lenticrypt/__init__.py
lenticrypt/__main__.py
lenticrypt/iowrapper.py
lenticrypt/lenticrypt.py
lenticrypt/logger.py
lenticrypt/progress.py
lenticrypt/utils.py
lenticrypt.egg-info/PKG-INFO
lenticrypt.egg-info/SOURCES.txt
lenticrypt.egg-info/dependency_links.txt
lenticrypt.egg-info/entry_points.txt
lenticrypt.egg-info/top_level.txt